rsmorphy_lemmatizer/__init__.py
rsmorphy_lemmatizer/_version.py
rsmorphy_lemmatizer/rsmorphy_lemmatizer.cp311-win_amd64.pyd
rsmorphy_lemmatizer/rsmorphy_dict_ru/grammemes.json.gz
rsmorphy_lemmatizer/rsmorphy_dict_ru/gramtab-opencorpora-ext.json.gz
rsmorphy_lemmatizer/rsmorphy_dict_ru/gramtab-opencorpora-int.json.gz
rsmorphy_lemmatizer/rsmorphy_dict_ru/meta.json.gz
rsmorphy_lemmatizer/rsmorphy_dict_ru/p_t_given_w.intdawg.gz
rsmorphy_lemmatizer/rsmorphy_dict_ru/paradigms.array.gz
rsmorphy_lemmatizer/rsmorphy_dict_ru/prediction-prefixes.dawg.gz
rsmorphy_lemmatizer/rsmorphy_dict_ru/prediction-suffixes-0.dawg.gz
rsmorphy_lemmatizer/rsmorphy_dict_ru/prediction-suffixes-1.dawg.gz
rsmorphy_lemmatizer/rsmorphy_dict_ru/prediction-suffixes-2.dawg.gz
rsmorphy_lemmatizer/rsmorphy_dict_ru/suffixes.json.gz
rsmorphy_lemmatizer/rsmorphy_dict_ru/words.dawg.gz
rsmorphy_lemmatizer-0.1.7.dist-info/LICENSE
rsmorphy_lemmatizer-0.1.7.dist-info/METADATA
rsmorphy_lemmatizer-0.1.7.dist-info/WHEEL
rsmorphy_lemmatizer-0.1.7.dist-info/top_level.txt
rsmorphy_lemmatizer-0.1.7.dist-info/RECORD
