Metadata-Version: 2.1
Name: rsmorphy-lemmatizer
Version: 0.1.7
Summary: Simple class for lemmatize (word normal form) russian words, based on rsmorphy. Support scikit-learn transformer interface.
Author-email: GAlexander <g.alexander.box@gmail.com>
Project-URL: Homepage, https://github.com/g-alexander/rsmorphy_lemmatizer
Project-URL: Bug Tracker, https://github.com/g-alexander/rsmorphy_lemmatizer/issues
Classifier: Programming Language :: Python :: 3
Classifier: License :: OSI Approved :: MIT License
Classifier: Operating System :: POSIX :: Linux
Requires-Python: <3.14.0,>=3.8
License-File: LICENSE
Requires-Dist: scikit-learn
